genealogy/__init__.py
genealogy-0.0.3.dist-info/LICENSE
genealogy-0.0.3.dist-info/METADATA
genealogy-0.0.3.dist-info/WHEEL
genealogy-0.0.3.dist-info/top_level.txt
genealogy-0.0.3.dist-info/RECORD
