Metadata-Version: 2.1
Name: genealogy
Version: 0.0.3
Summary: A package for recording Genealogy.
Home-page: https://github.com/kibaffo33/genealogy
Author: Robert Williams
Author-email: robertedwardwilliams@me.com
License: UNKNOWN
Platform: UNKNOWN
Classifier: Programming Language :: Python :: 3
Classifier: License :: OSI Approved :: MIT License
Classifier: Operating System :: OS Independent
